pncpy/_utils.pyx
pncpy/_File.pyx
pncpy/_Dimension.pyx
pncpy/_utils.cpython-310-darwin.so
pncpy/__init__.py
pncpy/_Variable.pyx
pncpy/_Variable.pxd
pncpy/_File.cpython-310-darwin.so
pncpy/_Dimension.pxd
pncpy/_Variable.cpython-310-darwin.so
pncpy/_File.pxd
pncpy/_Dimension.cpython-310-darwin.so
pncpy/_utils.pxd
pncpy/.dylibs/libhwloc.15.dylib
pncpy/.dylibs/libpmpi.12.dylib
pncpy/.dylibs/libmpi.12.dylib
pncpy/.dylibs/libmpifort.12.dylib
pncpy/.dylibs/libgfortran.5.dylib
pncpy/.dylibs/libpnetcdf.4.dylib
pncpy/.dylibs/libmpicxx.12.dylib
pncpy/.dylibs/libquadmath.0.dylib
pncpy/.dylibs/libgcc_s.1.1.dylib
pncpy-0.0.3.dist-info/RECORD
pncpy-0.0.3.dist-info/LICENSE
pncpy-0.0.3.dist-info/WHEEL
pncpy-0.0.3.dist-info/top_level.txt
pncpy-0.0.3.dist-info/METADATA
